pt_vid/Constants.py
pt_vid/Evaluate.py
pt_vid/Plot.py
pt_vid/Trainer.py
pt_vid/__init__.py
pt_vid/data/Cleaner.py
pt_vid/data/Delexicalizer.py
pt_vid/data/Sampler.py
pt_vid/data/Splitter.py
pt_vid/data/Tokenizer.py
pt_vid/data/__init__.py
pt_vid/data/cleaning/CleanupStrategy.py
pt_vid/data/cleaning/DetokenizerStrategy.py
pt_vid/data/cleaning/FastTextLangDetect.py
pt_vid/data/cleaning/SizeBasedFiltering.py
pt_vid/data/cleaning/Strategy.py
pt_vid/data/cleaning/thresholds.json
pt_vid/data/generators/GenerateLaw.py
pt_vid/data/generators/GenerateLiterature.py
pt_vid/data/generators/GenerateNews.py
pt_vid/data/generators/GeneratePolitics.py
pt_vid/data/generators/GenerateSocialMedia.py
pt_vid/data/generators/GenerateWeb.py
pt_vid/data/generators/Generator.py
pt_vid/data/generators/__init__.py
pt_vid/data/splitters/DefaultSplitterStrategy.py
pt_vid/data/splitters/Strategy.py
pt_vid/data/splitters/__init__.py
pt_vid/data/splitters/default_test_splits.json
pt_vid/entity/CorporaStats.py
pt_vid/entity/DatasetStats.py
pt_vid/entity/Entity.py
pt_vid/entity/InferenceResult.py
pt_vid/entity/NgramsTrainingResult.py
pt_vid/entity/NgramsTrainingScenario.py
pt_vid/entity/TestResult.py
pt_vid/entity/TrainingResult.py
pt_vid/entity/TrainingScenario.py
pt_vid/entity/VIDDataset.py
pt_vid/exception/NonPortugueseTextException.py
pt_vid/exception/__init__.py
pt_vid/models/Model.py
pt_vid/models/Ngrams.py
pt_vid/models/Transformer.py
pt_vid/models/__init__.py
pt_vid/stats/CorporaStats.py
pt_vid/stats/__init__.py
pt_vid/trainer/HFTrainer.py
pt_vid/trainer/NgramsTrainer.py
pt_vid/trainer/Strategy.py
pt_vid/trainer/__init__.py
pt_vid/trainer/ngrams_scenarios.json
pt_vid-0.1.dev1.dist-info/LICENSE
pt_vid-0.1.dev1.dist-info/METADATA
pt_vid-0.1.dev1.dist-info/WHEEL
pt_vid-0.1.dev1.dist-info/top_level.txt
pt_vid-0.1.dev1.dist-info/RECORD
